{
  "categoryId": "gear",
  "entityId": "331132",
  "slug": "331132-storm-scepter",
  "title": {
    "de-DE": "Storm Scepter",
    "en-US": "Storm Scepter",
    "es-ES": "Storm Scepter",
    "fr-FR": "Storm Scepter",
    "id-ID": "Storm Scepter",
    "ja-JP": "ストームセプター",
    "ko-KR": "Storm Scepter",
    "pl-PL": "Storm Scepter",
    "pt-BR": "Storm Scepter",
    "ru-RU": "Storm Scepter",
    "th-TH": "Storm Scepter",
    "tr-TR": "Storm Scepter",
    "uk-UA": "Storm Scepter",
    "vi-VN": "Storm Scepter",
    "zh-Hans": "Storm Scepter",
    "zh-Hant": "Storm Scepter"
  },
  "subtitle": {
    "de-DE": "Ungewöhnlich / Zepter / Hauptwaffe / Lv. 60",
    "en-US": "Uncommon / Scepter / Main Weapon / Lv. 60",
    "es-ES": "Poco común / Cetro / Arma principal / Lv. 60",
    "fr-FR": "Peu commun / Sceptre / Arme principale / Lv. 60",
    "id-ID": "Tidak Biasa / Tongkat Kerajaan / Senjata Utama / Lv. 60",
    "ja-JP": "アンコモン / セプター / メイン武器 / Lv. 60",
    "ko-KR": "고급 / 셉터 / 주무기 / Lv. 60",
    "pl-PL": "Niezwykły / Berło / Broń główna / Lv. 60",
    "pt-BR": "Incomum / Cetro / Arma Principal / Lv. 60",
    "ru-RU": "Необычный / Скипетр / Основное оружие / Lv. 60",
    "th-TH": "ไม่ธรรมดา / คทา / อาวุธหลัก / Lv. 60",
    "tr-TR": "Yaygın Olmayan / Asa / Ana Silah / Lv. 60",
    "uk-UA": "Незвичайний / Скіпетр / Основна зброя / Lv. 60",
    "vi-VN": "Không thường / Vương Trượng / Vũ khí chính / Lv. 60",
    "zh-Hans": "罕见 / 权杖 / 主武器 / Lv. 60",
    "zh-Hant": "罕見 / 權杖 / 主武器 / Lv. 60"
  },
  "icon": "/generated/assets/game/item/Equipment/SCEPTER_330013.png",
  "rarity": "UNCOMMON",
  "tags": [
    "UNCOMMON",
    "GEAR",
    "SCEPTER",
    "MAIN_WEAPON"
  ],
  "heroImage": "/generated/assets/game/item/Equipment/SCEPTER_330013.png",
  "overview": [
    {
      "labelKey": "field.id",
      "value": "331132"
    },
    {
      "labelKey": "field.grade",
      "value": "UNCOMMON"
    },
    {
      "labelKey": "field.type",
      "value": "GEAR"
    },
    {
      "labelKey": "field.gearType",
      "value": "SCEPTER"
    },
    {
      "labelKey": "field.level",
      "value": "60"
    }
  ],
  "sections": [
    {
      "titleKey": "detail.section.gearStats",
      "type": "stats",
      "items": [
        {
          "labelKey": "field.attackDamage",
          "value": "142"
        },
        {
          "labelKey": "field.attackSpeed",
          "value": "20"
        },
        {
          "labelKey": "CriticalChance / FLAT",
          "value": "12"
        }
      ]
    },
    {
      "titleKey": "detail.section.raw",
      "type": "table",
      "columns": [
        {
          "labelKey": "field.name"
        },
        {
          "labelKey": "field.value"
        }
      ],
      "rows": [
        [
          "ItemKey",
          "331132"
        ],
        [
          "ITEMTYPE",
          "GEAR"
        ],
        [
          "GRADE",
          "UNCOMMON"
        ],
        [
          "PARTS",
          "MAIN_WEAPON"
        ],
        [
          "GEARTYPE",
          "SCEPTER"
        ],
        [
          "GearGroup",
          "WEAPON"
        ],
        [
          "ItemSynthesisType",
          "Gear"
        ],
        [
          "NameKey",
          "ItemName_330013"
        ],
        [
          "GearKey",
          "331132"
        ],
        [
          "Level",
          "60"
        ],
        [
          "IsSteamItem",
          "true"
        ],
        [
          "IconPath",
          "SCEPTER_330013"
        ],
        [
          "IsDeletedInServer",
          "true"
        ],
        [
          "display_name",
          "Storm Scepter"
        ],
        [
          "localized_name",
          "{\"en\": \"Storm Scepter\", \"ja\": \"ストームセプター\"}"
        ],
        [
          "localized_description",
          "{\"en\": \"\", \"ja\": \"\"}"
        ],
        [
          "mono_fields",
          "{}"
        ]
      ]
    }
  ],
  "source": {
    "table": "ItemInfoData"
  }
}
