{
  "categoryId": "gear",
  "entityId": "334142",
  "slug": "334142-limitless-scepter",
  "title": {
    "ja": "リミットレスセプター",
    "en": "Limitless Scepter"
  },
  "subtitle": {
    "en": "Immortal / Scepter / Main Weapon / Lv. 65",
    "ja": "イモータル / セプター / メイン武器 / Lv. 65"
  },
  "icon": "/generated/assets/game/item/Equipment/SCEPTER_330014.png",
  "rarity": "IMMORTAL",
  "tags": [
    "IMMORTAL",
    "GEAR",
    "SCEPTER",
    "MAIN_WEAPON"
  ],
  "heroImage": "/generated/assets/game/item/Equipment/SCEPTER_330014.png",
  "overview": [
    {
      "labelKey": "field.id",
      "value": "334142"
    },
    {
      "labelKey": "field.grade",
      "value": "IMMORTAL"
    },
    {
      "labelKey": "field.type",
      "value": "GEAR"
    },
    {
      "labelKey": "field.gearType",
      "value": "SCEPTER"
    },
    {
      "labelKey": "field.level",
      "value": "65"
    }
  ],
  "sections": [
    {
      "titleKey": "detail.section.gearStats",
      "type": "stats",
      "items": [
        {
          "labelKey": "field.attackDamage",
          "value": "328"
        },
        {
          "labelKey": "field.attackSpeed",
          "value": "20"
        },
        {
          "labelKey": "CooldownReduction / FLAT",
          "value": "71"
        },
        {
          "labelKey": "CriticalDamage / FLAT",
          "value": "658"
        }
      ]
    },
    {
      "titleKey": "detail.section.raw",
      "type": "table",
      "columns": [
        {
          "labelKey": "field.name"
        },
        {
          "labelKey": "field.value"
        }
      ],
      "rows": [
        [
          "ItemKey",
          "334142"
        ],
        [
          "ITEMTYPE",
          "GEAR"
        ],
        [
          "GRADE",
          "IMMORTAL"
        ],
        [
          "PARTS",
          "MAIN_WEAPON"
        ],
        [
          "GEARTYPE",
          "SCEPTER"
        ],
        [
          "GearGroup",
          "WEAPON"
        ],
        [
          "ItemSynthesisType",
          "Gear"
        ],
        [
          "NameKey",
          "ItemName_330014"
        ],
        [
          "GearKey",
          "334142"
        ],
        [
          "Level",
          "65"
        ],
        [
          "IsSteamItem",
          "true"
        ],
        [
          "IconPath",
          "SCEPTER_330014"
        ],
        [
          "IsDeletedInServer",
          "true"
        ],
        [
          "display_name",
          "Limitless Scepter"
        ],
        [
          "localized_name",
          "{\"en\": \"Limitless Scepter\", \"ja\": \"リミットレスセプター\"}"
        ],
        [
          "localized_description",
          "{\"en\": \"\", \"ja\": \"\"}"
        ],
        [
          "mono_fields",
          "{}"
        ]
      ]
    }
  ],
  "source": {
    "table": "ItemInfoData"
  }
}
