{
  "categoryId": "gear",
  "entityId": "351122",
  "slug": "351122-hero-axe",
  "title": {
    "ja": "ヒーローアックス",
    "en": "Hero Axe"
  },
  "subtitle": {
    "en": "Uncommon / Axe / Main Weapon / Lv. 55",
    "ja": "アンコモン / 斧 / メイン武器 / Lv. 55"
  },
  "icon": "/generated/assets/game/item/Equipment/AXE_350012.png",
  "rarity": "UNCOMMON",
  "tags": [
    "UNCOMMON",
    "GEAR",
    "AXE",
    "MAIN_WEAPON"
  ],
  "heroImage": "/generated/assets/game/item/Equipment/AXE_350012.png",
  "overview": [
    {
      "labelKey": "field.id",
      "value": "351122"
    },
    {
      "labelKey": "field.grade",
      "value": "UNCOMMON"
    },
    {
      "labelKey": "field.type",
      "value": "GEAR"
    },
    {
      "labelKey": "field.gearType",
      "value": "AXE"
    },
    {
      "labelKey": "field.level",
      "value": "55"
    }
  ],
  "sections": [
    {
      "titleKey": "detail.section.gearStats",
      "type": "stats",
      "items": [
        {
          "labelKey": "field.attackDamage",
          "value": "185"
        },
        {
          "labelKey": "field.attackSpeed",
          "value": "20"
        },
        {
          "labelKey": "AttackSpeed / MULTIPLICATIVE",
          "value": "120"
        }
      ]
    },
    {
      "titleKey": "detail.section.raw",
      "type": "table",
      "columns": [
        {
          "labelKey": "field.name"
        },
        {
          "labelKey": "field.value"
        }
      ],
      "rows": [
        [
          "ItemKey",
          "351122"
        ],
        [
          "ITEMTYPE",
          "GEAR"
        ],
        [
          "GRADE",
          "UNCOMMON"
        ],
        [
          "PARTS",
          "MAIN_WEAPON"
        ],
        [
          "GEARTYPE",
          "AXE"
        ],
        [
          "GearGroup",
          "WEAPON"
        ],
        [
          "ItemSynthesisType",
          "Gear"
        ],
        [
          "NameKey",
          "ItemName_350012"
        ],
        [
          "GearKey",
          "351122"
        ],
        [
          "Level",
          "55"
        ],
        [
          "IsSteamItem",
          "true"
        ],
        [
          "IconPath",
          "AXE_350012"
        ],
        [
          "IsDeletedInServer",
          "true"
        ],
        [
          "display_name",
          "Hero Axe"
        ],
        [
          "localized_name",
          "{\"en\": \"Hero Axe\", \"ja\": \"ヒーローアックス\"}"
        ],
        [
          "localized_description",
          "{\"en\": \"\", \"ja\": \"\"}"
        ],
        [
          "mono_fields",
          "{}"
        ]
      ]
    }
  ],
  "source": {
    "table": "ItemInfoData"
  }
}
