{
  "categoryId": "gear",
  "entityId": "351121",
  "slug": "351121-hero-axe",
  "title": {
    "de-DE": "Hero Axe",
    "en-US": "Hero Axe",
    "es-ES": "Hero Axe",
    "fr-FR": "Hero Axe",
    "id-ID": "Hero Axe",
    "ja-JP": "ヒーローアックス",
    "ko-KR": "Hero Axe",
    "pl-PL": "Hero Axe",
    "pt-BR": "Hero Axe",
    "ru-RU": "Hero Axe",
    "th-TH": "Hero Axe",
    "tr-TR": "Hero Axe",
    "uk-UA": "Hero Axe",
    "vi-VN": "Hero Axe",
    "zh-Hans": "Hero Axe",
    "zh-Hant": "Hero Axe"
  },
  "subtitle": {
    "de-DE": "Ungewöhnlich / Axt / Hauptwaffe / Lv. 55",
    "en-US": "Uncommon / Axe / Main Weapon / Lv. 55",
    "es-ES": "Poco común / Hacha / Arma principal / Lv. 55",
    "fr-FR": "Peu commun / Hache / Arme principale / Lv. 55",
    "id-ID": "Tidak Biasa / Kapak / Senjata Utama / Lv. 55",
    "ja-JP": "アンコモン / 斧 / メイン武器 / Lv. 55",
    "ko-KR": "고급 / 도끼 / 주무기 / Lv. 55",
    "pl-PL": "Niezwykły / Topór / Broń główna / Lv. 55",
    "pt-BR": "Incomum / Machado / Arma Principal / Lv. 55",
    "ru-RU": "Необычный / Топор / Основное оружие / Lv. 55",
    "th-TH": "ไม่ธรรมดา / ขวาน / อาวุธหลัก / Lv. 55",
    "tr-TR": "Yaygın Olmayan / Balta / Ana Silah / Lv. 55",
    "uk-UA": "Незвичайний / Сокира / Основна зброя / Lv. 55",
    "vi-VN": "Không thường / Rìu / Vũ khí chính / Lv. 55",
    "zh-Hans": "罕见 / 斧头 / 主武器 / Lv. 55",
    "zh-Hant": "罕見 / 斧頭 / 主武器 / Lv. 55"
  },
  "icon": "/generated/assets/game/item/Equipment/AXE_350012.png",
  "rarity": "UNCOMMON",
  "tags": [
    "UNCOMMON",
    "GEAR",
    "AXE",
    "MAIN_WEAPON"
  ],
  "heroImage": "/generated/assets/game/item/Equipment/AXE_350012.png",
  "overview": [
    {
      "labelKey": "field.id",
      "value": "351121"
    },
    {
      "labelKey": "field.grade",
      "value": "UNCOMMON"
    },
    {
      "labelKey": "field.type",
      "value": "GEAR"
    },
    {
      "labelKey": "field.gearType",
      "value": "AXE"
    },
    {
      "labelKey": "field.level",
      "value": "55"
    }
  ],
  "sections": [
    {
      "titleKey": "detail.section.gearStats",
      "type": "stats",
      "items": [
        {
          "labelKey": "field.attackDamage",
          "value": "185"
        },
        {
          "labelKey": "field.attackSpeed",
          "value": "20"
        },
        {
          "labelKey": "AttackSpeed / MULTIPLICATIVE",
          "value": "120"
        }
      ]
    },
    {
      "titleKey": "detail.section.raw",
      "type": "table",
      "columns": [
        {
          "labelKey": "field.name"
        },
        {
          "labelKey": "field.value"
        }
      ],
      "rows": [
        [
          "ItemKey",
          "351121"
        ],
        [
          "ITEMTYPE",
          "GEAR"
        ],
        [
          "GRADE",
          "UNCOMMON"
        ],
        [
          "PARTS",
          "MAIN_WEAPON"
        ],
        [
          "GEARTYPE",
          "AXE"
        ],
        [
          "GearGroup",
          "WEAPON"
        ],
        [
          "ItemSynthesisType",
          "Gear"
        ],
        [
          "NameKey",
          "ItemName_350012"
        ],
        [
          "GearKey",
          "351121"
        ],
        [
          "Level",
          "55"
        ],
        [
          "IsSteamItem",
          "true"
        ],
        [
          "IconPath",
          "AXE_350012"
        ],
        [
          "IsDeletedInServer",
          "true"
        ],
        [
          "display_name",
          "Hero Axe"
        ],
        [
          "localized_name",
          "{\"en\": \"Hero Axe\", \"ja\": \"ヒーローアックス\"}"
        ],
        [
          "localized_description",
          "{\"en\": \"\", \"ja\": \"\"}"
        ],
        [
          "mono_fields",
          "{}"
        ]
      ]
    }
  ],
  "source": {
    "table": "ItemInfoData"
  }
}
