{
  "categoryId": "gear",
  "entityId": "407142",
  "slug": "407142-radiant-shield",
  "title": {
    "de-DE": "Radiant Shield",
    "en-US": "Radiant Shield",
    "es-ES": "Radiant Shield",
    "fr-FR": "Radiant Shield",
    "id-ID": "Radiant Shield",
    "ja-JP": "レイディアントシールド",
    "ko-KR": "Radiant Shield",
    "pl-PL": "Radiant Shield",
    "pt-BR": "Radiant Shield",
    "ru-RU": "Radiant Shield",
    "th-TH": "Radiant Shield",
    "tr-TR": "Radiant Shield",
    "uk-UA": "Radiant Shield",
    "vi-VN": "Radiant Shield",
    "zh-Hans": "Radiant Shield",
    "zh-Hant": "Radiant Shield"
  },
  "subtitle": {
    "de-DE": "Himmlisch / Schild / Nebenwaffe / Lv. 65",
    "en-US": "Celestial / Shield / Sub Weapon / Lv. 65",
    "es-ES": "Celestial / Escudo / Arma secundaria / Lv. 65",
    "fr-FR": "Céleste / Bouclier / Arme secondaire / Lv. 65",
    "id-ID": "Surgawi / Perisai / Senjata Pendamping / Lv. 65",
    "ja-JP": "セレスティアル / シールド / サブ武器 / Lv. 65",
    "ko-KR": "천상 / 방패 / 보조무기 / Lv. 65",
    "pl-PL": "Niebiański / Tarcza / Broń dodatkowa / Lv. 65",
    "pt-BR": "Celestial / Escudo / Arma Secundária / Lv. 65",
    "ru-RU": "Небесный / Щит / Доп. оружие / Lv. 65",
    "th-TH": "สวรรค์ / โล่ / อาวุธรอง / Lv. 65",
    "tr-TR": "Göksel / Kalkan / Yardımcı Silah / Lv. 65",
    "uk-UA": "Небесний / Щит / Додаткова зброя / Lv. 65",
    "vi-VN": "Thiên giới / Khiên / Vũ khí phụ / Lv. 65",
    "zh-Hans": "天界 / 盾牌 / 副武器 / Lv. 65",
    "zh-Hant": "天界 / 盾牌 / 副武器 / Lv. 65"
  },
  "icon": "/generated/assets/game/item/Equipment/SHIELD_400014.png",
  "rarity": "CELESTIAL",
  "tags": [
    "CELESTIAL",
    "GEAR",
    "SHIELD",
    "SUB_WEAPON"
  ],
  "heroImage": "/generated/assets/game/item/Equipment/SHIELD_400014.png",
  "overview": [
    {
      "labelKey": "field.id",
      "value": "407142"
    },
    {
      "labelKey": "field.grade",
      "value": "CELESTIAL"
    },
    {
      "labelKey": "field.type",
      "value": "GEAR"
    },
    {
      "labelKey": "field.gearType",
      "value": "SHIELD"
    },
    {
      "labelKey": "field.level",
      "value": "65"
    }
  ],
  "sections": [
    {
      "titleKey": "detail.section.gearStats",
      "type": "stats",
      "items": [
        {
          "labelKey": "field.attackDamage",
          "value": "325"
        },
        {
          "labelKey": "field.attackSpeed",
          "value": "-"
        },
        {
          "labelKey": "Armor / FLAT",
          "value": "4621"
        },
        {
          "labelKey": "DamageReduction / FLAT",
          "value": "133"
        },
        {
          "labelKey": "BlockChance / FLAT",
          "value": "195"
        }
      ]
    },
    {
      "titleKey": "detail.section.raw",
      "type": "table",
      "columns": [
        {
          "labelKey": "field.name"
        },
        {
          "labelKey": "field.value"
        }
      ],
      "rows": [
        [
          "ItemKey",
          "407142"
        ],
        [
          "ITEMTYPE",
          "GEAR"
        ],
        [
          "GRADE",
          "CELESTIAL"
        ],
        [
          "PARTS",
          "SUB_WEAPON"
        ],
        [
          "GEARTYPE",
          "SHIELD"
        ],
        [
          "GearGroup",
          "WEAPON"
        ],
        [
          "ItemSynthesisType",
          "Gear"
        ],
        [
          "NameKey",
          "ItemName_400014"
        ],
        [
          "GearKey",
          "407142"
        ],
        [
          "Level",
          "65"
        ],
        [
          "IsSteamItem",
          "true"
        ],
        [
          "IconPath",
          "SHIELD_400014"
        ],
        [
          "IsDeletedInServer",
          "true"
        ],
        [
          "display_name",
          "Radiant Shield"
        ],
        [
          "localized_name",
          "{\"en\": \"Radiant Shield\", \"ja\": \"レイディアントシールド\"}"
        ],
        [
          "localized_description",
          "{\"en\": \"\", \"ja\": \"\"}"
        ],
        [
          "mono_fields",
          "{}"
        ]
      ]
    }
  ],
  "source": {
    "table": "ItemInfoData"
  }
}
