{
  "categoryId": "gear",
  "entityId": "447162",
  "slug": "447162-poison-bolt",
  "title": {
    "de-DE": "Poison Bolt",
    "en-US": "Poison Bolt",
    "es-ES": "Poison Bolt",
    "fr-FR": "Poison Bolt",
    "id-ID": "Poison Bolt",
    "ja-JP": "ポイズンボルト",
    "ko-KR": "Poison Bolt",
    "pl-PL": "Poison Bolt",
    "pt-BR": "Poison Bolt",
    "ru-RU": "Poison Bolt",
    "th-TH": "Poison Bolt",
    "tr-TR": "Poison Bolt",
    "uk-UA": "Poison Bolt",
    "vi-VN": "Poison Bolt",
    "zh-Hans": "Poison Bolt",
    "zh-Hant": "Poison Bolt"
  },
  "subtitle": {
    "de-DE": "Himmlisch / Bolzen / Nebenwaffe / Lv. 75",
    "en-US": "Celestial / Bolt / Sub Weapon / Lv. 75",
    "es-ES": "Celestial / Saeta / Arma secundaria / Lv. 75",
    "fr-FR": "Céleste / Carreau / Arme secondaire / Lv. 75",
    "id-ID": "Surgawi / Baut / Senjata Pendamping / Lv. 75",
    "ja-JP": "セレスティアル / クロスボウボルト / サブ武器 / Lv. 75",
    "ko-KR": "천상 / 석궁 화살 / 보조무기 / Lv. 75",
    "pl-PL": "Niebiański / Bełt / Broń dodatkowa / Lv. 75",
    "pt-BR": "Celestial / Flecha de Besta / Arma Secundária / Lv. 75",
    "ru-RU": "Небесный / Болт / Доп. оружие / Lv. 75",
    "th-TH": "สวรรค์ / ลูกธนูหน้าไม้ / อาวุธรอง / Lv. 75",
    "tr-TR": "Göksel / Arbalet Oku / Yardımcı Silah / Lv. 75",
    "uk-UA": "Небесний / Болт / Додаткова зброя / Lv. 75",
    "vi-VN": "Thiên giới / Tên nỏ / Vũ khí phụ / Lv. 75",
    "zh-Hans": "天界 / 弩箭 / 副武器 / Lv. 75",
    "zh-Hant": "天界 / 弩箭 / 副武器 / Lv. 75"
  },
  "icon": "/generated/assets/game/item/Equipment/BOLT_440016.png",
  "rarity": "CELESTIAL",
  "tags": [
    "CELESTIAL",
    "GEAR",
    "BOLT",
    "SUB_WEAPON"
  ],
  "heroImage": "/generated/assets/game/item/Equipment/BOLT_440016.png",
  "overview": [
    {
      "labelKey": "field.id",
      "value": "447162"
    },
    {
      "labelKey": "field.grade",
      "value": "CELESTIAL"
    },
    {
      "labelKey": "field.type",
      "value": "GEAR"
    },
    {
      "labelKey": "field.gearType",
      "value": "BOLT"
    },
    {
      "labelKey": "field.level",
      "value": "75"
    }
  ],
  "sections": [
    {
      "titleKey": "detail.section.gearStats",
      "type": "stats",
      "items": [
        {
          "labelKey": "field.attackDamage",
          "value": "2237"
        },
        {
          "labelKey": "field.attackSpeed",
          "value": "-"
        },
        {
          "labelKey": "AttackDamage / FLAT",
          "value": "163"
        },
        {
          "labelKey": "CriticalDamage / FLAT",
          "value": "770"
        },
        {
          "labelKey": "CooldownReduction / FLAT",
          "value": "64"
        }
      ]
    },
    {
      "titleKey": "detail.section.raw",
      "type": "table",
      "columns": [
        {
          "labelKey": "field.name"
        },
        {
          "labelKey": "field.value"
        }
      ],
      "rows": [
        [
          "ItemKey",
          "447162"
        ],
        [
          "ITEMTYPE",
          "GEAR"
        ],
        [
          "GRADE",
          "CELESTIAL"
        ],
        [
          "PARTS",
          "SUB_WEAPON"
        ],
        [
          "GEARTYPE",
          "BOLT"
        ],
        [
          "GearGroup",
          "WEAPON"
        ],
        [
          "ItemSynthesisType",
          "Gear"
        ],
        [
          "NameKey",
          "ItemName_440016"
        ],
        [
          "GearKey",
          "447162"
        ],
        [
          "Level",
          "75"
        ],
        [
          "IsSteamItem",
          "true"
        ],
        [
          "IconPath",
          "BOLT_440016"
        ],
        [
          "IsDeletedInServer",
          "true"
        ],
        [
          "display_name",
          "Poison Bolt"
        ],
        [
          "localized_name",
          "{\"en\": \"Poison Bolt\", \"ja\": \"ポイズンボルト\"}"
        ],
        [
          "localized_description",
          "{\"en\": \"\", \"ja\": \"\"}"
        ],
        [
          "mono_fields",
          "{}"
        ]
      ]
    }
  ],
  "source": {
    "table": "ItemInfoData"
  }
}
