{
  "categoryId": "gear",
  "entityId": "452142",
  "slug": "452142-limitless-hatchet",
  "title": {
    "de-DE": "Limitless Hatchet",
    "en-US": "Limitless Hatchet",
    "es-ES": "Limitless Hatchet",
    "fr-FR": "Limitless Hatchet",
    "id-ID": "Limitless Hatchet",
    "ja-JP": "リミットレスハチェット",
    "ko-KR": "Limitless Hatchet",
    "pl-PL": "Limitless Hatchet",
    "pt-BR": "Limitless Hatchet",
    "ru-RU": "Limitless Hatchet",
    "th-TH": "Limitless Hatchet",
    "tr-TR": "Limitless Hatchet",
    "uk-UA": "Limitless Hatchet",
    "vi-VN": "Limitless Hatchet",
    "zh-Hans": "Limitless Hatchet",
    "zh-Hant": "Limitless Hatchet"
  },
  "subtitle": {
    "de-DE": "Selten / Handbeil / Nebenwaffe / Lv. 65",
    "en-US": "Rare / Hatchet / Sub Weapon / Lv. 65",
    "es-ES": "Raro / Hacheta / Arma secundaria / Lv. 65",
    "fr-FR": "Rare / Hachette / Arme secondaire / Lv. 65",
    "id-ID": "Langka / Kapak / Senjata Pendamping / Lv. 65",
    "ja-JP": "レア / 手斧 / サブ武器 / Lv. 65",
    "ko-KR": "희귀 / 손도끼 / 보조무기 / Lv. 65",
    "pl-PL": "Rzadki / Toporek / Broń dodatkowa / Lv. 65",
    "pt-BR": "Raro / Machadinha / Arma Secundária / Lv. 65",
    "ru-RU": "Редкий / Хатчет / Доп. оружие / Lv. 65",
    "th-TH": "หายาก / ขวานมือ / อาวุธรอง / Lv. 65",
    "tr-TR": "Nadir / El Baltası / Yardımcı Silah / Lv. 65",
    "uk-UA": "Рідкісний / Сокирка / Додаткова зброя / Lv. 65",
    "vi-VN": "Hiếm / Rìu Tay / Vũ khí phụ / Lv. 65",
    "zh-Hans": "稀有 / 手斧 / 副武器 / Lv. 65",
    "zh-Hant": "稀有 / 手斧 / 副武器 / Lv. 65"
  },
  "icon": "/generated/assets/game/item/Equipment/HATCHET_450014.png",
  "rarity": "RARE",
  "tags": [
    "RARE",
    "GEAR",
    "HATCHET",
    "SUB_WEAPON"
  ],
  "heroImage": "/generated/assets/game/item/Equipment/HATCHET_450014.png",
  "overview": [
    {
      "labelKey": "field.id",
      "value": "452142"
    },
    {
      "labelKey": "field.grade",
      "value": "RARE"
    },
    {
      "labelKey": "field.type",
      "value": "GEAR"
    },
    {
      "labelKey": "field.gearType",
      "value": "HATCHET"
    },
    {
      "labelKey": "field.level",
      "value": "65"
    }
  ],
  "sections": [
    {
      "titleKey": "detail.section.gearStats",
      "type": "stats",
      "items": [
        {
          "labelKey": "field.attackDamage",
          "value": "952"
        },
        {
          "labelKey": "field.attackSpeed",
          "value": "-"
        },
        {
          "labelKey": "AttackDamage / FLAT",
          "value": "29"
        }
      ]
    },
    {
      "titleKey": "detail.section.raw",
      "type": "table",
      "columns": [
        {
          "labelKey": "field.name"
        },
        {
          "labelKey": "field.value"
        }
      ],
      "rows": [
        [
          "ItemKey",
          "452142"
        ],
        [
          "ITEMTYPE",
          "GEAR"
        ],
        [
          "GRADE",
          "RARE"
        ],
        [
          "PARTS",
          "SUB_WEAPON"
        ],
        [
          "GEARTYPE",
          "HATCHET"
        ],
        [
          "GearGroup",
          "WEAPON"
        ],
        [
          "ItemSynthesisType",
          "Gear"
        ],
        [
          "NameKey",
          "ItemName_450014"
        ],
        [
          "GearKey",
          "452142"
        ],
        [
          "Level",
          "65"
        ],
        [
          "IsSteamItem",
          "true"
        ],
        [
          "IconPath",
          "HATCHET_450014"
        ],
        [
          "IsDeletedInServer",
          "true"
        ],
        [
          "display_name",
          "Limitless Hatchet"
        ],
        [
          "localized_name",
          "{\"en\": \"Limitless Hatchet\", \"ja\": \"リミットレスハチェット\"}"
        ],
        [
          "localized_description",
          "{\"en\": \"\", \"ja\": \"\"}"
        ],
        [
          "mono_fields",
          "{}"
        ]
      ]
    }
  ],
  "source": {
    "table": "ItemInfoData"
  }
}
