{
  "categoryId": "gear",
  "entityId": "500015",
  "slug": "500015-void-helmet",
  "title": {
    "ja": "ヴォイドヘルム",
    "en": "Void Helmet"
  },
  "subtitle": {
    "en": "Common / Helmet / HELMET / Lv. 70",
    "ja": "コモン / ヘルメット / HELMET / Lv. 70"
  },
  "icon": "/generated/assets/game/item/Equipment/HELMET_500015.png",
  "rarity": "COMMON",
  "tags": [
    "COMMON",
    "GEAR",
    "HELMET",
    "HELMET"
  ],
  "heroImage": "/generated/assets/game/item/Equipment/HELMET_500015.png",
  "overview": [
    {
      "labelKey": "field.id",
      "value": "500015"
    },
    {
      "labelKey": "field.grade",
      "value": "COMMON"
    },
    {
      "labelKey": "field.type",
      "value": "GEAR"
    },
    {
      "labelKey": "field.gearType",
      "value": "HELMET"
    },
    {
      "labelKey": "field.level",
      "value": "70"
    }
  ],
  "sections": [
    {
      "titleKey": "detail.section.gearStats",
      "type": "stats",
      "items": [
        {
          "labelKey": "field.attackDamage",
          "value": "397"
        },
        {
          "labelKey": "field.attackSpeed",
          "value": "-"
        }
      ]
    },
    {
      "titleKey": "detail.section.raw",
      "type": "table",
      "columns": [
        {
          "labelKey": "field.name"
        },
        {
          "labelKey": "field.value"
        }
      ],
      "rows": [
        [
          "ItemKey",
          "500015"
        ],
        [
          "ITEMTYPE",
          "GEAR"
        ],
        [
          "GRADE",
          "COMMON"
        ],
        [
          "PARTS",
          "HELMET"
        ],
        [
          "GEARTYPE",
          "HELMET"
        ],
        [
          "GearGroup",
          "ARMOR"
        ],
        [
          "ItemSynthesisType",
          "Gear"
        ],
        [
          "NameKey",
          "ItemName_500015"
        ],
        [
          "GearKey",
          "500015"
        ],
        [
          "Level",
          "70"
        ],
        [
          "IsSteamItem",
          "true"
        ],
        [
          "IconPath",
          "HELMET_500015"
        ],
        [
          "IsDeletedInServer",
          "true"
        ],
        [
          "display_name",
          "Void Helmet"
        ],
        [
          "localized_name",
          "{\"en\": \"Void Helmet\", \"ja\": \"ヴォイドヘルム\"}"
        ],
        [
          "localized_description",
          "{\"en\": \"\", \"ja\": \"\"}"
        ],
        [
          "mono_fields",
          "{}"
        ]
      ]
    }
  ],
  "source": {
    "table": "ItemInfoData"
  }
}
