{
  "categoryId": "gear",
  "entityId": "534072",
  "slug": "534072-war-boots",
  "title": {
    "de-DE": "War Boots",
    "en-US": "War Boots",
    "es-ES": "War Boots",
    "fr-FR": "War Boots",
    "id-ID": "War Boots",
    "ja-JP": "ウォーブーツ",
    "ko-KR": "War Boots",
    "pl-PL": "War Boots",
    "pt-BR": "War Boots",
    "ru-RU": "War Boots",
    "th-TH": "War Boots",
    "tr-TR": "War Boots",
    "uk-UA": "War Boots",
    "vi-VN": "War Boots",
    "zh-Hans": "War Boots",
    "zh-Hant": "War Boots"
  },
  "subtitle": {
    "de-DE": "Unsterblich / Stiefel / BOOTS / Lv. 30",
    "en-US": "Immortal / Boots / BOOTS / Lv. 30",
    "es-ES": "Inmortal / Botas / BOOTS / Lv. 30",
    "fr-FR": "Immortel / Bottes / BOOTS / Lv. 30",
    "id-ID": "Abadi / Sepatu / BOOTS / Lv. 30",
    "ja-JP": "イモータル / ブーツ / BOOTS / Lv. 30",
    "ko-KR": "불멸 / 신발 / BOOTS / Lv. 30",
    "pl-PL": "Nieśmiertelny / Buty / BOOTS / Lv. 30",
    "pt-BR": "Imortal / Botas / BOOTS / Lv. 30",
    "ru-RU": "Бессмертный / Сапоги / BOOTS / Lv. 30",
    "th-TH": "อมตะ / รองเท้า / BOOTS / Lv. 30",
    "tr-TR": "Ölümsüz / Çizmeler / BOOTS / Lv. 30",
    "uk-UA": "Безсмертний / Чоботи / BOOTS / Lv. 30",
    "vi-VN": "Bất tử / Giày / BOOTS / Lv. 30",
    "zh-Hans": "不朽 / 靴子 / BOOTS / Lv. 30",
    "zh-Hant": "不朽 / 靴子 / BOOTS / Lv. 30"
  },
  "icon": "/generated/assets/game/item/Equipment/BOOTS_530007.png",
  "rarity": "IMMORTAL",
  "tags": [
    "IMMORTAL",
    "GEAR",
    "BOOTS",
    "BOOTS"
  ],
  "heroImage": "/generated/assets/game/item/Equipment/BOOTS_530007.png",
  "overview": [
    {
      "labelKey": "field.id",
      "value": "534072"
    },
    {
      "labelKey": "field.grade",
      "value": "IMMORTAL"
    },
    {
      "labelKey": "field.type",
      "value": "GEAR"
    },
    {
      "labelKey": "field.gearType",
      "value": "BOOTS"
    },
    {
      "labelKey": "field.level",
      "value": "30"
    }
  ],
  "sections": [
    {
      "titleKey": "detail.section.gearStats",
      "type": "stats",
      "items": [
        {
          "labelKey": "field.attackDamage",
          "value": "109"
        },
        {
          "labelKey": "field.attackSpeed",
          "value": "0"
        },
        {
          "labelKey": "Armor / FLAT",
          "value": "83"
        },
        {
          "labelKey": "MovementSpeed / FLAT",
          "value": "53"
        }
      ]
    },
    {
      "titleKey": "detail.section.raw",
      "type": "table",
      "columns": [
        {
          "labelKey": "field.name"
        },
        {
          "labelKey": "field.value"
        }
      ],
      "rows": [
        [
          "ItemKey",
          "534072"
        ],
        [
          "ITEMTYPE",
          "GEAR"
        ],
        [
          "GRADE",
          "IMMORTAL"
        ],
        [
          "PARTS",
          "BOOTS"
        ],
        [
          "GEARTYPE",
          "BOOTS"
        ],
        [
          "GearGroup",
          "ARMOR"
        ],
        [
          "ItemSynthesisType",
          "Gear"
        ],
        [
          "NameKey",
          "ItemName_530007"
        ],
        [
          "GearKey",
          "534072"
        ],
        [
          "Level",
          "30"
        ],
        [
          "IsSteamItem",
          "true"
        ],
        [
          "IconPath",
          "BOOTS_530007"
        ],
        [
          "IsDeletedInServer",
          "true"
        ],
        [
          "display_name",
          "War Boots"
        ],
        [
          "localized_name",
          "{\"en\": \"War Boots\", \"ja\": \"ウォーブーツ\"}"
        ],
        [
          "localized_description",
          "{\"en\": \"\", \"ja\": \"\"}"
        ],
        [
          "mono_fields",
          "{}"
        ]
      ]
    }
  ],
  "source": {
    "table": "ItemInfoData"
  }
}
