{
  "categoryId": "gear",
  "entityId": "603081",
  "slug": "603081-amber-pendant",
  "title": {
    "de-DE": "Amber Pendant",
    "en-US": "Amber Pendant",
    "es-ES": "Amber Pendant",
    "fr-FR": "Amber Pendant",
    "id-ID": "Amber Pendant",
    "ja-JP": "アンバーペンダント",
    "ko-KR": "Amber Pendant",
    "pl-PL": "Amber Pendant",
    "pt-BR": "Amber Pendant",
    "ru-RU": "Amber Pendant",
    "th-TH": "Amber Pendant",
    "tr-TR": "Amber Pendant",
    "uk-UA": "Amber Pendant",
    "vi-VN": "Amber Pendant",
    "zh-Hans": "Amber Pendant",
    "zh-Hant": "Amber Pendant"
  },
  "subtitle": {
    "de-DE": "Legendär / Amulett / AMULET / Lv. 35",
    "en-US": "Legendary / Amulet / AMULET / Lv. 35",
    "es-ES": "Legendario / Amuleto / AMULET / Lv. 35",
    "fr-FR": "Légendaire / Amulette / AMULET / Lv. 35",
    "id-ID": "Legendaris / Jimat / AMULET / Lv. 35",
    "ja-JP": "レジェンダリー / アミュレット / AMULET / Lv. 35",
    "ko-KR": "전설 / 목걸이 / AMULET / Lv. 35",
    "pl-PL": "Legendarny / Amulet / AMULET / Lv. 35",
    "pt-BR": "Lendário / Amuleto / AMULET / Lv. 35",
    "ru-RU": "Легендарный / Амулет / AMULET / Lv. 35",
    "th-TH": "ตำนาน / สร้อยคอ / AMULET / Lv. 35",
    "tr-TR": "Efsanevi / Muska / AMULET / Lv. 35",
    "uk-UA": "Легендарний / Амулет / AMULET / Lv. 35",
    "vi-VN": "Huyền thoại / Bùa hộ mệnh / AMULET / Lv. 35",
    "zh-Hans": "传奇 / 护身符 / AMULET / Lv. 35",
    "zh-Hant": "傳奇 / 護身符 / AMULET / Lv. 35"
  },
  "icon": "/generated/assets/game/item/Equipment/AMULET_600008.png",
  "rarity": "LEGENDARY",
  "tags": [
    "LEGENDARY",
    "GEAR",
    "AMULET",
    "AMULET"
  ],
  "heroImage": "/generated/assets/game/item/Equipment/AMULET_600008.png",
  "overview": [
    {
      "labelKey": "field.id",
      "value": "603081"
    },
    {
      "labelKey": "field.grade",
      "value": "LEGENDARY"
    },
    {
      "labelKey": "field.type",
      "value": "GEAR"
    },
    {
      "labelKey": "field.gearType",
      "value": "AMULET"
    },
    {
      "labelKey": "field.level",
      "value": "35"
    }
  ],
  "sections": [
    {
      "titleKey": "detail.section.gearStats",
      "type": "stats",
      "items": [
        {
          "labelKey": "field.attackDamage",
          "value": "0"
        },
        {
          "labelKey": "field.attackSpeed",
          "value": "0"
        },
        {
          "labelKey": "AttackSpeed / ADDITIVE",
          "value": "103"
        },
        {
          "labelKey": "CooldownReduction / FLAT",
          "value": "35"
        }
      ]
    },
    {
      "titleKey": "detail.section.raw",
      "type": "table",
      "columns": [
        {
          "labelKey": "field.name"
        },
        {
          "labelKey": "field.value"
        }
      ],
      "rows": [
        [
          "ItemKey",
          "603081"
        ],
        [
          "ITEMTYPE",
          "GEAR"
        ],
        [
          "GRADE",
          "LEGENDARY"
        ],
        [
          "PARTS",
          "AMULET"
        ],
        [
          "GEARTYPE",
          "AMULET"
        ],
        [
          "GearGroup",
          "ACCESSORY"
        ],
        [
          "ItemSynthesisType",
          "Accessory"
        ],
        [
          "NameKey",
          "ItemName_600008"
        ],
        [
          "GearKey",
          "603081"
        ],
        [
          "Level",
          "35"
        ],
        [
          "IsSteamItem",
          "true"
        ],
        [
          "IconPath",
          "AMULET_600008"
        ],
        [
          "IsDeletedInServer",
          "true"
        ],
        [
          "display_name",
          "Amber Pendant"
        ],
        [
          "localized_name",
          "{\"en\": \"Amber Pendant\", \"ja\": \"アンバーペンダント\"}"
        ],
        [
          "localized_description",
          "{\"en\": \"\", \"ja\": \"\"}"
        ],
        [
          "mono_fields",
          "{}"
        ]
      ]
    }
  ],
  "source": {
    "table": "ItemInfoData"
  }
}
