{
  "categoryId": "gear",
  "entityId": "613192",
  "slug": "613192-abyss-earring",
  "title": {
    "ja": "アビスピアス",
    "en": "Abyss Earring"
  },
  "subtitle": {
    "en": "Legendary / Earing / EARING / Lv. 90",
    "ja": "レジェンダリー / イヤリング / EARING / Lv. 90"
  },
  "icon": "/generated/assets/game/item/Equipment/EARING_610019.png",
  "rarity": "LEGENDARY",
  "tags": [
    "LEGENDARY",
    "GEAR",
    "EARING",
    "EARING"
  ],
  "heroImage": "/generated/assets/game/item/Equipment/EARING_610019.png",
  "overview": [
    {
      "labelKey": "field.id",
      "value": "613192"
    },
    {
      "labelKey": "field.grade",
      "value": "LEGENDARY"
    },
    {
      "labelKey": "field.type",
      "value": "GEAR"
    },
    {
      "labelKey": "field.gearType",
      "value": "EARING"
    },
    {
      "labelKey": "field.level",
      "value": "90"
    }
  ],
  "sections": [
    {
      "titleKey": "detail.section.gearStats",
      "type": "stats",
      "items": [
        {
          "labelKey": "field.attackDamage",
          "value": "0"
        },
        {
          "labelKey": "field.attackSpeed",
          "value": "-"
        },
        {
          "labelKey": "IncreaseExpAmount / ADDITIVE",
          "value": "100"
        },
        {
          "labelKey": "HpLeech / FLAT",
          "value": "15"
        }
      ]
    },
    {
      "titleKey": "detail.section.raw",
      "type": "table",
      "columns": [
        {
          "labelKey": "field.name"
        },
        {
          "labelKey": "field.value"
        }
      ],
      "rows": [
        [
          "ItemKey",
          "613192"
        ],
        [
          "ITEMTYPE",
          "GEAR"
        ],
        [
          "GRADE",
          "LEGENDARY"
        ],
        [
          "PARTS",
          "EARING"
        ],
        [
          "GEARTYPE",
          "EARING"
        ],
        [
          "GearGroup",
          "ACCESSORY"
        ],
        [
          "ItemSynthesisType",
          "Accessory"
        ],
        [
          "NameKey",
          "ItemName_610019"
        ],
        [
          "GearKey",
          "613192"
        ],
        [
          "Level",
          "90"
        ],
        [
          "IsSteamItem",
          "true"
        ],
        [
          "IconPath",
          "EARING_610019"
        ],
        [
          "IsDeletedInServer",
          "true"
        ],
        [
          "display_name",
          "Abyss Earring"
        ],
        [
          "localized_name",
          "{\"en\": \"Abyss Earring\", \"ja\": \"アビスピアス\"}"
        ],
        [
          "localized_description",
          "{\"en\": \"\", \"ja\": \"\"}"
        ],
        [
          "mono_fields",
          "{}"
        ]
      ]
    }
  ],
  "source": {
    "table": "ItemInfoData"
  }
}
