{
  "categoryId": "gear",
  "entityId": "634011",
  "slug": "634011-copper-bracer",
  "title": {
    "de-DE": "Copper Bracer",
    "en-US": "Copper Bracer",
    "es-ES": "Copper Bracer",
    "fr-FR": "Copper Bracer",
    "id-ID": "Copper Bracer",
    "ja-JP": "コパーブレーサー",
    "ko-KR": "Copper Bracer",
    "pl-PL": "Copper Bracer",
    "pt-BR": "Copper Bracer",
    "ru-RU": "Copper Bracer",
    "th-TH": "Copper Bracer",
    "tr-TR": "Copper Bracer",
    "uk-UA": "Copper Bracer",
    "vi-VN": "Copper Bracer",
    "zh-Hans": "Copper Bracer",
    "zh-Hant": "Copper Bracer"
  },
  "subtitle": {
    "de-DE": "Unsterblich / Armschiene / BRACER / Lv. 1",
    "en-US": "Immortal / Bracer / BRACER / Lv. 1",
    "es-ES": "Inmortal / Brazalete / BRACER / Lv. 1",
    "fr-FR": "Immortel / Brassard / BRACER / Lv. 1",
    "id-ID": "Abadi / Gelang / BRACER / Lv. 1",
    "ja-JP": "イモータル / ブレイサー / BRACER / Lv. 1",
    "ko-KR": "불멸 / 팔찌 / BRACER / Lv. 1",
    "pl-PL": "Nieśmiertelny / Karwasz / BRACER / Lv. 1",
    "pt-BR": "Imortal / Braçadeira / BRACER / Lv. 1",
    "ru-RU": "Бессмертный / Наруч / BRACER / Lv. 1",
    "th-TH": "อมตะ / สายรัดข้อมือ / BRACER / Lv. 1",
    "tr-TR": "Ölümsüz / Kolçak / BRACER / Lv. 1",
    "uk-UA": "Безсмертний / Наруч / BRACER / Lv. 1",
    "vi-VN": "Bất tử / Vòng tay / BRACER / Lv. 1",
    "zh-Hans": "不朽 / 护腕 / BRACER / Lv. 1",
    "zh-Hant": "不朽 / 護腕 / BRACER / Lv. 1"
  },
  "icon": "/generated/assets/game/item/Equipment/BRACER_630001.png",
  "rarity": "IMMORTAL",
  "tags": [
    "IMMORTAL",
    "GEAR",
    "BRACER",
    "BRACER"
  ],
  "heroImage": "/generated/assets/game/item/Equipment/BRACER_630001.png",
  "overview": [
    {
      "labelKey": "field.id",
      "value": "634011"
    },
    {
      "labelKey": "field.grade",
      "value": "IMMORTAL"
    },
    {
      "labelKey": "field.type",
      "value": "GEAR"
    },
    {
      "labelKey": "field.gearType",
      "value": "BRACER"
    },
    {
      "labelKey": "field.level",
      "value": "1"
    }
  ],
  "sections": [
    {
      "titleKey": "detail.section.sources",
      "type": "table",
      "columns": [
        {
          "labelKey": "field.chest"
        },
        {
          "labelKey": "field.percent"
        },
        {
          "labelKey": "field.stage"
        },
        {
          "labelKey": "field.drop"
        }
      ],
      "rows": [
        [
          {
            "de-DE": "DropKey 3121014",
            "en-US": "DropKey 3121014",
            "es-ES": "DropKey 3121014",
            "fr-FR": "DropKey 3121014",
            "id-ID": "DropKey 3121014",
            "ja-JP": "DropKey 3121014",
            "ko-KR": "DropKey 3121014",
            "pl-PL": "DropKey 3121014",
            "pt-BR": "DropKey 3121014",
            "ru-RU": "DropKey 3121014",
            "th-TH": "DropKey 3121014",
            "tr-TR": "DropKey 3121014",
            "uk-UA": "DropKey 3121014",
            "vi-VN": "DropKey 3121014",
            "zh-Hans": "DropKey 3121014",
            "zh-Hant": "DropKey 3121014"
          },
          "34.48%",
          {
            "de-DE": "-",
            "en-US": "-",
            "es-ES": "-",
            "fr-FR": "-",
            "id-ID": "-",
            "ja-JP": "-",
            "ko-KR": "-",
            "pl-PL": "-",
            "pt-BR": "-",
            "ru-RU": "-",
            "th-TH": "-",
            "tr-TR": "-",
            "uk-UA": "-",
            "vi-VN": "-",
            "zh-Hans": "-",
            "zh-Hant": "-"
          },
          "-"
        ],
        [
          {
            "de-DE": "DropKey 3601007",
            "en-US": "DropKey 3601007",
            "es-ES": "DropKey 3601007",
            "fr-FR": "DropKey 3601007",
            "id-ID": "DropKey 3601007",
            "ja-JP": "DropKey 3601007",
            "ko-KR": "DropKey 3601007",
            "pl-PL": "DropKey 3601007",
            "pt-BR": "DropKey 3601007",
            "ru-RU": "DropKey 3601007",
            "th-TH": "DropKey 3601007",
            "tr-TR": "DropKey 3601007",
            "uk-UA": "DropKey 3601007",
            "vi-VN": "DropKey 3601007",
            "zh-Hans": "DropKey 3601007",
            "zh-Hant": "DropKey 3601007"
          },
          "0.202%",
          {
            "de-DE": "-",
            "en-US": "-",
            "es-ES": "-",
            "fr-FR": "-",
            "id-ID": "-",
            "ja-JP": "-",
            "ko-KR": "-",
            "pl-PL": "-",
            "pt-BR": "-",
            "ru-RU": "-",
            "th-TH": "-",
            "tr-TR": "-",
            "uk-UA": "-",
            "vi-VN": "-",
            "zh-Hans": "-",
            "zh-Hant": "-"
          },
          "-"
        ],
        [
          {
            "de-DE": "DropKey 3700001",
            "en-US": "DropKey 3700001",
            "es-ES": "DropKey 3700001",
            "fr-FR": "DropKey 3700001",
            "id-ID": "DropKey 3700001",
            "ja-JP": "DropKey 3700001",
            "ko-KR": "DropKey 3700001",
            "pl-PL": "DropKey 3700001",
            "pt-BR": "DropKey 3700001",
            "ru-RU": "DropKey 3700001",
            "th-TH": "DropKey 3700001",
            "tr-TR": "DropKey 3700001",
            "uk-UA": "DropKey 3700001",
            "vi-VN": "DropKey 3700001",
            "zh-Hans": "DropKey 3700001",
            "zh-Hant": "DropKey 3700001"
          },
          "0.005754%",
          {
            "de-DE": "-",
            "en-US": "-",
            "es-ES": "-",
            "fr-FR": "-",
            "id-ID": "-",
            "ja-JP": "-",
            "ko-KR": "-",
            "pl-PL": "-",
            "pt-BR": "-",
            "ru-RU": "-",
            "th-TH": "-",
            "tr-TR": "-",
            "uk-UA": "-",
            "vi-VN": "-",
            "zh-Hans": "-",
            "zh-Hant": "-"
          },
          "-"
        ]
      ]
    },
    {
      "titleKey": "detail.section.gearStats",
      "type": "stats",
      "items": [
        {
          "labelKey": "field.attackDamage",
          "value": "0"
        },
        {
          "labelKey": "field.attackSpeed",
          "value": "-"
        },
        {
          "labelKey": "DamageAbsorption / FLAT",
          "value": "34"
        },
        {
          "labelKey": "DodgeChance / FLAT",
          "value": "32"
        }
      ]
    },
    {
      "titleKey": "detail.section.raw",
      "type": "table",
      "columns": [
        {
          "labelKey": "field.name"
        },
        {
          "labelKey": "field.value"
        }
      ],
      "rows": [
        [
          "ItemKey",
          "634011"
        ],
        [
          "ITEMTYPE",
          "GEAR"
        ],
        [
          "GRADE",
          "IMMORTAL"
        ],
        [
          "PARTS",
          "BRACER"
        ],
        [
          "GEARTYPE",
          "BRACER"
        ],
        [
          "GearGroup",
          "ACCESSORY"
        ],
        [
          "ItemSynthesisType",
          "Accessory"
        ],
        [
          "NameKey",
          "ItemName_630001"
        ],
        [
          "GearKey",
          "634011"
        ],
        [
          "Level",
          "1"
        ],
        [
          "IsSteamItem",
          "true"
        ],
        [
          "IconPath",
          "BRACER_630001"
        ],
        [
          "IsCanExchangeMarketable",
          "true"
        ],
        [
          "display_name",
          "Copper Bracer"
        ],
        [
          "localized_name",
          "{\"en\": \"Copper Bracer\", \"ja\": \"コパーブレーサー\"}"
        ],
        [
          "localized_description",
          "{\"en\": \"Platinum bracer Description\", \"ja\": \"Platinum bracer Description\"}"
        ],
        [
          "mono_name",
          "Platinum bracer"
        ],
        [
          "mono_fields",
          "{\"name\": \"Platinum bracer\", \"description\": \"Platinum bracer Description\", \"display_type\": \"Bracer - Lv. 1\", \"type\": \"gear\", \"rarity\": \"immortal\", \"parts\": \"bracer\", \"level\": \"1\"}"
        ]
      ]
    }
  ],
  "source": {
    "table": "ItemInfoData"
  }
}
